{"cameraMode":{"drawMode":0,"name":"Shaded","section":"Shading Mode"},"sceneLighting":false,"audioPlay":false,"sceneViewState":{"showFog":true,"showMaterialUpdate":false,"showSkybox":false,"showFlares":true,"showImageEffects":true,"showParticleSystems":true},"in2DMode":false,"pivot":{"x":-92.11244201660156,"y":1.1387224197387696,"z":69.03465270996094},"rotation":{"x":-0.36020541191101076,"y":0.6112777590751648,"z":-0.365429550409317,"w":-0.6025390028953552},"size":4.935521602630615,"orthographic":false}